connect_lib/__init__.py
connect_lib/action.py
connect_lib/client/__init__.py
connect_lib/client/action_client.py
connect_lib/client/client_manager.py
connect_lib/client/request_client.py
connect_lib/client/validation_client.py
connect_lib/config_base.py
connect_lib/consts.py
connect_lib/exceptions.py
connect_lib/flows/__init__.py
connect_lib/flows/action_flow.py
connect_lib/flows/base_flow.py
connect_lib/flows/process_flow.py
connect_lib/flows/request_flow.py
connect_lib/flows/validation_flow.py
connect_lib/logger.py
connect_lib/messages.py
connect_lib/request.py
extaasy-0.1.5.dist-info/METADATA
extaasy-0.1.5.dist-info/WHEEL
extaasy-0.1.5.dist-info/LICENSE
extaasy-0.1.5.dist-info/RECORD
